{
  "columbus579": [
    {
      "unit": "1204",
      "building": "50-columbus",
      "size": "545",
      "available_date": "2025-10-18",
      "floorplan_type": "studio",
      "floorplan_link": "",
      "floorplan_note": "",
      "prices": [
        {
          "price": 3170,
          "price_range": "",
          "date_fetched": "2025-07-23 04:32:03"
        }
      ]
    },
    {
      "unit": "1611",
      "building": "50-columbus",
      "size": "546",
      "available_date": "2025-09-30",
      "floorplan_type": "studio",
      "floorplan_link": "",
      "floorplan_note": "",
      "prices": [
        {
          "price": 3120,
          "price_range": "",
          "date_fetched": "2025-07-23 04:32:07"
        }
      ]
    },
    {
      "unit": "1008",
      "building": "50-columbus",
      "size": "678",
      "available_date": "2025-09-21",
      "floorplan_type": "1b1b",
      "floorplan_link": "",
      "floorplan_note": "",
      "prices": [
        {
          "price": 3450,
          "price_range": "",
          "date_fetched": "2025-07-23 04:32:11"
        }
      ]
    },
    {
      "unit": "2606",
      "building": "50-columbus",
      "size": "765",
      "available_date": "2025-09-05",
      "floorplan_type": "1b1b",
      "floorplan_link": "",
      "floorplan_note": "",
      "prices": [
        {
          "price": 3785,
          "price_range": "",
          "date_fetched": "2025-07-23 04:32:14"
        }
      ]
    },
    {
      "unit": "ph11",
      "building": "70-columbus",
      "size": "545",
      "available_date": "2025-09-23",
      "floorplan_type": "studio",
      "floorplan_link": "",
      "floorplan_note": "",
      "prices": [
        {
          "price": 3340,
          "price_range": "",
          "date_fetched": "2025-07-23 04:32:22"
        }
      ]
    },
    {
      "unit": "3211",
      "building": "70-columbus",
      "size": "545",
      "available_date": "2025-10-15",
      "floorplan_type": "studio",
      "floorplan_link": "",
      "floorplan_note": "",
      "prices": [
        {
          "price": 3100,
          "price_range": "",
          "date_fetched": "2025-07-23 04:32:22"
        }
      ]
    },
    {
      "unit": "4901",
      "building": "70-columbus",
      "size": "660",
      "available_date": "1900-01-01",
      "floorplan_type": "1b1b",
      "floorplan_link": "",
      "floorplan_note": "",
      "prices": [
        {
          "price": 3925,
          "price_range": "",
          "date_fetched": "2025-07-23 04:32:26"
        }
      ]
    },
    {
      "unit": "4001",
      "building": "70-columbus",
      "size": "660",
      "available_date": "2025-08-02",
      "floorplan_type": "1b1b",
      "floorplan_link": "",
      "floorplan_note": "",
      "prices": [
        {
          "price": 3835,
          "price_range": "",
          "date_fetched": "2025-07-23 04:32:26"
        }
      ]
    },
    {
      "unit": "3501",
      "building": "70-columbus",
      "size": "660",
      "available_date": "2025-08-06",
      "floorplan_type": "1b1b",
      "floorplan_link": "",
      "floorplan_note": "",
      "prices": [
        {
          "price": 3785,
          "price_range": "",
          "date_fetched": "2025-07-23 04:32:26"
        }
      ]
    },
    {
      "unit": "5001",
      "building": "70-columbus",
      "size": "660",
      "available_date": "2025-10-15",
      "floorplan_type": "1b1b",
      "floorplan_link": "",
      "floorplan_note": "",
      "prices": [
        {
          "price": 3935,
          "price_range": "",
          "date_fetched": "2025-07-23 04:32:26"
        }
      ]
    },
    {
      "unit": "4509",
      "building": "70-columbus",
      "size": "662",
      "available_date": "2025-08-19",
      "floorplan_type": "1b1b",
      "floorplan_link": "",
      "floorplan_note": "",
      "prices": [
        {
          "price": 3905,
          "price_range": "",
          "date_fetched": "2025-07-23 04:32:30"
        }
      ]
    },
    {
      "unit": "2903",
      "building": "70-columbus",
      "size": "669",
      "available_date": "2025-09-09",
      "floorplan_type": "1b1b",
      "floorplan_link": "",
      "floorplan_note": "",
      "prices": [
        {
          "price": 3765,
          "price_range": "",
          "date_fetched": "2025-07-23 04:32:33"
        }
      ]
    },
    {
      "unit": "3903",
      "building": "70-columbus",
      "size": "669",
      "available_date": "2025-09-13",
      "floorplan_type": "1b1b",
      "floorplan_link": "",
      "floorplan_note": "",
      "prices": [
        {
          "price": 4065,
          "price_range": "",
          "date_fetched": "2025-07-23 04:32:33"
        }
      ]
    },
    {
      "unit": "ph05",
      "building": "70-columbus",
      "size": "672",
      "available_date": "2025-09-11",
      "floorplan_type": "1b1b",
      "floorplan_link": "",
      "floorplan_note": "",
      "prices": [
        {
          "price": 4265,
          "price_range": "",
          "date_fetched": "2025-07-23 04:32:37"
        }
      ]
    },
    {
      "unit": "5005",
      "building": "70-columbus",
      "size": "821",
      "available_date": "2025-09-03",
      "floorplan_type": "1b1b",
      "floorplan_link": "",
      "floorplan_note": "",
      "prices": [
        {
          "price": 4550,
          "price_range": "",
          "date_fetched": "2025-07-23 04:32:41"
        }
      ]
    },
    {
      "unit": "4704",
      "building": "70-columbus",
      "size": "1086",
      "available_date": "1900-01-01",
      "floorplan_type": "2b2b",
      "floorplan_link": "",
      "floorplan_note": "",
      "prices": [
        {
          "price": 6195,
          "price_range": "",
          "date_fetched": "2025-07-23 04:32:45"
        }
      ]
    },
    {
      "unit": "4207",
      "building": "90-columbus",
      "size": "541",
      "available_date": "2025-08-14",
      "floorplan_type": "studio",
      "floorplan_link": "",
      "floorplan_note": "",
      "prices": [
        {
          "price": 3660,
          "price_range": "",
          "date_fetched": "2025-07-23 04:32:53"
        }
      ]
    },
    {
      "unit": "3807",
      "building": "90-columbus",
      "size": "541",
      "available_date": "2025-08-20",
      "floorplan_type": "studio",
      "floorplan_link": "",
      "floorplan_note": "",
      "prices": [
        {
          "price": 3495,
          "price_range": "",
          "date_fetched": "2025-07-23 04:32:53"
        }
      ]
    },
    {
      "unit": "4609",
      "building": "90-columbus",
      "size": "676",
      "available_date": "1900-01-01",
      "floorplan_type": "1b1b",
      "floorplan_link": "",
      "floorplan_note": "",
      "prices": [
        {
          "price": 3950,
          "price_range": "",
          "date_fetched": "2025-07-23 04:32:57"
        }
      ]
    },
    {
      "unit": "4309",
      "building": "90-columbus",
      "size": "676",
      "available_date": "2025-08-02",
      "floorplan_type": "1b1b",
      "floorplan_link": "",
      "floorplan_note": "",
      "prices": [
        {
          "price": 4020,
          "price_range": "",
          "date_fetched": "2025-07-23 04:32:57"
        }
      ]
    },
    {
      "unit": "4209",
      "building": "90-columbus",
      "size": "676",
      "available_date": "2025-08-09",
      "floorplan_type": "1b1b",
      "floorplan_link": "",
      "floorplan_note": "",
      "prices": [
        {
          "price": 4010,
          "price_range": "",
          "date_fetched": "2025-07-23 04:32:57"
        }
      ]
    },
    {
      "unit": "2701",
      "building": "90-columbus",
      "size": "690",
      "available_date": "2025-10-04",
      "floorplan_type": "1b1b",
      "floorplan_link": "",
      "floorplan_note": "",
      "prices": [
        {
          "price": 3835,
          "price_range": "",
          "date_fetched": "2025-07-23 04:33:01"
        }
      ]
    },
    {
      "unit": "2601",
      "building": "90-columbus",
      "size": "690",
      "available_date": "2025-10-15",
      "floorplan_type": "1b1b",
      "floorplan_link": "",
      "floorplan_note": "",
      "prices": [
        {
          "price": 3825,
          "price_range": "",
          "date_fetched": "2025-07-23 04:33:01"
        }
      ]
    },
    {
      "unit": "3001",
      "building": "90-columbus",
      "size": "690",
      "available_date": "2025-10-15",
      "floorplan_type": "1b1b",
      "floorplan_link": "",
      "floorplan_note": "",
      "prices": [
        {
          "price": 3865,
          "price_range": "",
          "date_fetched": "2025-07-23 04:33:01"
        }
      ]
    },
    {
      "unit": "4805",
      "building": "90-columbus",
      "size": "701",
      "available_date": "1900-01-01",
      "floorplan_type": "1b1b",
      "floorplan_link": "",
      "floorplan_note": "",
      "prices": [
        {
          "price": 4395,
          "price_range": "",
          "date_fetched": "2025-07-23 04:33:05"
        }
      ]
    },
    {
      "unit": "ph05",
      "building": "90-columbus",
      "size": "701",
      "available_date": "2025-09-04",
      "floorplan_type": "1b1b",
      "floorplan_link": "",
      "floorplan_note": "",
      "prices": [
        {
          "price": 4225,
          "price_range": "",
          "date_fetched": "2025-07-23 04:33:05"
        }
      ]
    },
    {
      "unit": "3905",
      "building": "90-columbus",
      "size": "701",
      "available_date": "2025-09-13",
      "floorplan_type": "1b1b",
      "floorplan_link": "",
      "floorplan_note": "",
      "prices": [
        {
          "price": 4105,
          "price_range": "",
          "date_fetched": "2025-07-23 04:33:05"
        }
      ]
    },
    {
      "unit": "5005",
      "building": "90-columbus",
      "size": "701",
      "available_date": "2025-10-04",
      "floorplan_type": "1b1b",
      "floorplan_link": "",
      "floorplan_note": "",
      "prices": [
        {
          "price": 4415,
          "price_range": "",
          "date_fetched": "2025-07-23 04:33:05"
        }
      ]
    },
    {
      "unit": "3608",
      "building": "90-columbus",
      "size": "704",
      "available_date": "2025-09-27",
      "floorplan_type": "1b1b",
      "floorplan_link": "",
      "floorplan_note": "",
      "prices": [
        {
          "price": 4400,
          "price_range": "",
          "date_fetched": "2025-07-23 04:33:09"
        }
      ]
    },
    {
      "unit": "4008",
      "building": "90-columbus",
      "size": "704",
      "available_date": "2025-09-27",
      "floorplan_type": "1b1b",
      "floorplan_link": "",
      "floorplan_note": "",
      "prices": [
        {
          "price": 4440,
          "price_range": "",
          "date_fetched": "2025-07-23 04:33:09"
        }
      ]
    },
    {
      "unit": "5006",
      "building": "90-columbus",
      "size": "708",
      "available_date": "2025-08-14",
      "floorplan_type": "1b1b",
      "floorplan_link": "",
      "floorplan_note": "",
      "prices": [
        {
          "price": 4240,
          "price_range": "",
          "date_fetched": "2025-07-23 04:33:13"
        }
      ]
    },
    {
      "unit": "1502",
      "building": "90-columbus",
      "size": "716",
      "available_date": "2025-10-15",
      "floorplan_type": "1b1b",
      "floorplan_link": "",
      "floorplan_note": "",
      "prices": [
        {
          "price": 3835,
          "price_range": "",
          "date_fetched": "2025-07-23 04:33:17"
        }
      ]
    },
    {
      "unit": "4804",
      "building": "90-columbus",
      "size": "1033",
      "available_date": "2025-09-13",
      "floorplan_type": "2b2b",
      "floorplan_link": "",
      "floorplan_note": "",
      "prices": [
        {
          "price": 6055,
          "price_range": "",
          "date_fetched": "2025-07-23 04:33:21"
        }
      ]
    },
    {
      "unit": "4210",
      "building": "90-columbus",
      "size": "1067",
      "available_date": "1900-01-01",
      "floorplan_type": "2b2b",
      "floorplan_link": "",
      "floorplan_note": "",
      "prices": [
        {
          "price": 5625,
          "price_range": "",
          "date_fetched": "2025-07-23 04:33:25"
        }
      ]
    },
    {
      "unit": "4710",
      "building": "90-columbus",
      "size": "1067",
      "available_date": "2025-07-30",
      "floorplan_type": "2b2b",
      "floorplan_link": "",
      "floorplan_note": "",
      "prices": [
        {
          "price": 5875,
          "price_range": "",
          "date_fetched": "2025-07-23 04:33:25"
        }
      ]
    },
    {
      "unit": "4010",
      "building": "90-columbus",
      "size": "1067",
      "available_date": "2025-08-06",
      "floorplan_type": "2b2b",
      "floorplan_link": "",
      "floorplan_note": "",
      "prices": [
        {
          "price": 5605,
          "price_range": "",
          "date_fetched": "2025-07-23 04:33:25"
        }
      ]
    },
    {
      "unit": "4610",
      "building": "90-columbus",
      "size": "1067",
      "available_date": "2025-08-20",
      "floorplan_type": "2b2b",
      "floorplan_link": "",
      "floorplan_note": "",
      "prices": [
        {
          "price": 5865,
          "price_range": "",
          "date_fetched": "2025-07-23 04:33:25"
        }
      ]
    },
    {
      "unit": "3003",
      "building": "90-columbus",
      "size": "1102",
      "available_date": "2025-08-26",
      "floorplan_type": "2b2b",
      "floorplan_link": "",
      "floorplan_note": "",
      "prices": [
        {
          "price": 5775,
          "price_range": "",
          "date_fetched": "2025-07-23 04:33:30"
        }
      ]
    },
    {
      "unit": "4603",
      "building": "90-columbus",
      "size": "1120",
      "available_date": "2025-08-06",
      "floorplan_type": "2b2b",
      "floorplan_link": "",
      "floorplan_note": "",
      "prices": [
        {
          "price": 6165,
          "price_range": "",
          "date_fetched": "2025-07-23 04:33:33"
        }
      ]
    },
    {
      "unit": "4903",
      "building": "90-columbus",
      "size": "1120",
      "available_date": "2025-08-06",
      "floorplan_type": "2b2b",
      "floorplan_link": "",
      "floorplan_note": "",
      "prices": [
        {
          "price": 6195,
          "price_range": "",
          "date_fetched": "2025-07-23 04:33:33"
        }
      ]
    },
    {
      "unit": "4703",
      "building": "90-columbus",
      "size": "1120",
      "available_date": "2025-09-13",
      "floorplan_type": "2b2b",
      "floorplan_link": "",
      "floorplan_note": "",
      "prices": [
        {
          "price": 6175,
          "price_range": "",
          "date_fetched": "2025-07-23 04:33:33"
        }
      ]
    },
    {
      "unit": "4803",
      "building": "90-columbus",
      "size": "1120",
      "available_date": "2025-09-17",
      "floorplan_type": "2b2b",
      "floorplan_link": "",
      "floorplan_note": "",
      "prices": [
        {
          "price": 6185,
          "price_range": "",
          "date_fetched": "2025-07-23 04:33:33"
        }
      ]
    }
  ],
  "haus25": [
    {
      "unit": "H25-2404",
      "building": "Haus25",
      "size": 527,
      "available_date": "2025-10-07",
      "floorplan_type": "0 bed, 1 bath",
      "floorplan_link": "https://verisresidential.com/wp-content/uploads/apartment-images/134143/Veris_H25_Floorplan_S7A.png",
      "floorplan_note": "Floorplan: S7A",
      "prices": [
        {
          "price": 3400,
          "price_range": "",
          "date_fetched": "2025-07-23 04:33:52"
        }
      ]
    },
    {
      "unit": "H25-2206",
      "building": "Haus25",
      "size": 464,
      "available_date": "2025-09-03",
      "floorplan_type": "0 bed, 1 bath",
      "floorplan_link": "https://verisresidential.com/wp-content/uploads/apartment-images/134143/Veris_H25_Floorplan_S2.png",
      "floorplan_note": "Floorplan: S2",
      "prices": [
        {
          "price": 3405,
          "price_range": "",
          "date_fetched": "2025-07-23 04:33:53"
        }
      ]
    },
    {
      "unit": "H25-3202",
      "building": "Haus25",
      "size": 444,
      "available_date": "2025-09-02",
      "floorplan_type": "0 bed, 1 bath",
      "floorplan_link": "https://verisresidential.com/wp-content/uploads/apartment-images/134143/Veris_H25_Floorplan_S1.png",
      "floorplan_note": "Floorplan: S1",
      "prices": [
        {
          "price": 3425,
          "price_range": "",
          "date_fetched": "2025-07-23 04:33:56"
        }
      ]
    },
    {
      "unit": "H25-3402",
      "building": "Haus25",
      "size": 444,
      "available_date": "2025-09-02",
      "floorplan_type": "0 bed, 1 bath",
      "floorplan_link": "https://verisresidential.com/wp-content/uploads/apartment-images/134143/Veris_H25_Floorplan_S1.png",
      "floorplan_note": "Floorplan: S1",
      "prices": [
        {
          "price": 3445,
          "price_range": "",
          "date_fetched": "2025-07-23 04:33:56"
        }
      ]
    },
    {
      "unit": "H25-3602",
      "building": "Haus25",
      "size": 444,
      "available_date": "2025-10-03",
      "floorplan_type": "0 bed, 1 bath",
      "floorplan_link": "https://verisresidential.com/wp-content/uploads/apartment-images/134143/Veris_H25_Floorplan_S1.png",
      "floorplan_note": "Floorplan: S1",
      "prices": [
        {
          "price": 3475,
          "price_range": "",
          "date_fetched": "2025-07-23 04:33:56"
        }
      ]
    },
    {
      "unit": "H25-3816",
      "building": "Haus25",
      "size": 466,
      "available_date": "2025-10-06",
      "floorplan_type": "0 bed, 1 bath",
      "floorplan_link": "https://verisresidential.com/wp-content/uploads/apartment-images/134143/Veris_H25_Floorplan_S3.png",
      "floorplan_note": "Floorplan: S3",
      "prices": [
        {
          "price": 3510,
          "price_range": "",
          "date_fetched": "2025-07-23 04:33:58"
        }
      ]
    },
    {
      "unit": "H25-5216",
      "building": "Haus25",
      "size": 466,
      "available_date": "2025-09-13",
      "floorplan_type": "0 bed, 1 bath",
      "floorplan_link": "https://verisresidential.com/wp-content/uploads/apartment-images/134143/Veris_H25_Floorplan_S3.png",
      "floorplan_note": "Floorplan: S3",
      "prices": [
        {
          "price": 3720,
          "price_range": "",
          "date_fetched": "2025-07-23 04:33:58"
        }
      ]
    },
    {
      "unit": "H25-3913",
      "building": "Haus25",
      "size": 475,
      "available_date": "2025-09-16",
      "floorplan_type": "0 bed, 1 bath",
      "floorplan_link": "https://verisresidential.com/wp-content/uploads/apartment-images/134143/Veris_H25_Floorplan_S4.png",
      "floorplan_note": "Floorplan: S4",
      "prices": [
        {
          "price": 3515,
          "price_range": "",
          "date_fetched": "2025-07-23 04:33:59"
        }
      ]
    },
    {
      "unit": "H25-5013",
      "building": "Haus25",
      "size": 475,
      "available_date": "2025-09-03",
      "floorplan_type": "0 bed, 1 bath",
      "floorplan_link": "https://verisresidential.com/wp-content/uploads/apartment-images/134143/Veris_H25_Floorplan_S4.png",
      "floorplan_note": "Floorplan: S4",
      "prices": [
        {
          "price": 3680,
          "price_range": "",
          "date_fetched": "2025-07-23 04:33:59"
        }
      ]
    },
    {
      "unit": "H25-5113",
      "building": "Haus25",
      "size": 475,
      "available_date": "2025-08-21",
      "floorplan_type": "0 bed, 1 bath",
      "floorplan_link": "https://verisresidential.com/wp-content/uploads/apartment-images/134143/Veris_H25_Floorplan_S4.png",
      "floorplan_note": "Floorplan: S4",
      "prices": [
        {
          "price": 3695,
          "price_range": "",
          "date_fetched": "2025-07-23 04:33:59"
        }
      ]
    },
    {
      "unit": "H25-5313",
      "building": "Haus25",
      "size": 475,
      "available_date": "2025-09-11",
      "floorplan_type": "0 bed, 1 bath",
      "floorplan_link": "https://verisresidential.com/wp-content/uploads/apartment-images/134143/Veris_H25_Floorplan_S4.png",
      "floorplan_note": "Floorplan: S4",
      "prices": [
        {
          "price": 3775,
          "price_range": "",
          "date_fetched": "2025-07-23 04:33:59"
        }
      ]
    },
    {
      "unit": "H25-5413",
      "building": "Haus25",
      "size": 475,
      "available_date": "2025-09-03",
      "floorplan_type": "0 bed, 1 bath",
      "floorplan_link": "https://verisresidential.com/wp-content/uploads/apartment-images/134143/Veris_H25_Floorplan_S4.png",
      "floorplan_note": "Floorplan: S4",
      "prices": [
        {
          "price": 3790,
          "price_range": "",
          "date_fetched": "2025-07-23 04:33:59"
        }
      ]
    },
    {
      "unit": "H25-5513",
      "building": "Haus25",
      "size": 475,
      "available_date": "2025-04-28",
      "floorplan_type": "0 bed, 1 bath",
      "floorplan_link": "https://verisresidential.com/wp-content/uploads/apartment-images/134143/Veris_H25_Floorplan_S4.png",
      "floorplan_note": "Floorplan: S4",
      "prices": [
        {
          "price": 3810,
          "price_range": "",
          "date_fetched": "2025-07-23 04:33:59"
        }
      ]
    },
    {
      "unit": "H25-3701",
      "building": "Haus25",
      "size": 545,
      "available_date": "2025-08-23",
      "floorplan_type": "0 bed, 1 bath",
      "floorplan_link": "https://verisresidential.com/wp-content/uploads/apartment-images/134143/Veris_H25_Floorplan_S8A.png",
      "floorplan_note": "Floorplan: S8A",
      "prices": [
        {
          "price": 3825,
          "price_range": "",
          "date_fetched": "2025-07-23 04:34:00"
        }
      ]
    },
    {
      "unit": "H25-1710",
      "building": "Haus25",
      "size": 548,
      "available_date": "2025-08-18",
      "floorplan_type": "0 bed, 1 bath",
      "floorplan_link": "https://verisresidential.com/wp-content/uploads/apartment-images/134143/Veris_H25_Floorplan_S6.png",
      "floorplan_note": "Floorplan: S6",
      "prices": [
        {
          "price": 3850,
          "price_range": "",
          "date_fetched": "2025-07-23 04:34:02"
        }
      ]
    },
    {
      "unit": "H25-5201",
      "building": "Haus25",
      "size": 575,
      "available_date": "2025-07-07",
      "floorplan_type": "0 bed, 1 bath",
      "floorplan_link": "https://verisresidential.com/wp-content/uploads/apartment-images/134143/Veris_H25_Floorplan_S8B.png",
      "floorplan_note": "Floorplan: S8B",
      "prices": [
        {
          "price": 4215,
          "price_range": "",
          "date_fetched": "2025-07-23 04:34:04"
        }
      ]
    },
    {
      "unit": "H25-1116",
      "building": "Haus25",
      "size": 751,
      "available_date": "2025-09-17",
      "floorplan_type": "1 bed, 1 bath",
      "floorplan_link": "https://verisresidential.com/wp-content/uploads/apartment-images/134143/Veris_H25_Floorplan_A8A.png",
      "floorplan_note": "Floorplan: A8A",
      "prices": [
        {
          "price": 4540,
          "price_range": "",
          "date_fetched": "2025-07-23 04:34:05"
        }
      ]
    },
    {
      "unit": "H25-0402",
      "building": "Haus25",
      "size": 799,
      "available_date": "2025-07-29",
      "floorplan_type": "1 bed, 1 bath",
      "floorplan_link": "https://verisresidential.com/wp-content/uploads/apartment-images/134143/Veris_H25_Floorplan_A9.png",
      "floorplan_note": "Floorplan: A9",
      "prices": [
        {
          "price": 4745,
          "price_range": "",
          "date_fetched": "2025-07-23 04:34:07"
        }
      ]
    },
    {
      "unit": "H25-2102",
      "building": "Haus25",
      "size": 799,
      "available_date": "2025-09-09",
      "floorplan_type": "1 bed, 1 bath",
      "floorplan_link": "https://verisresidential.com/wp-content/uploads/apartment-images/134143/Veris_H25_Floorplan_A9.png",
      "floorplan_note": "Floorplan: A9",
      "prices": [
        {
          "price": 4850,
          "price_range": "",
          "date_fetched": "2025-07-23 04:34:07"
        }
      ]
    },
    {
      "unit": "H25-1713",
      "building": "Haus25",
      "size": 745,
      "available_date": "2025-08-05",
      "floorplan_type": "1 bed, 1 bath",
      "floorplan_link": "https://verisresidential.com/wp-content/uploads/apartment-images/134143/Veris_H25_Floorplan_A4.png",
      "floorplan_note": "Floorplan: A4",
      "prices": [
        {
          "price": 4785,
          "price_range": "",
          "date_fetched": "2025-07-23 04:34:08"
        }
      ]
    },
    {
      "unit": "H25-1812",
      "building": "Haus25",
      "size": 744,
      "available_date": "2025-09-26",
      "floorplan_type": "1 bed, 1 bath",
      "floorplan_link": "https://verisresidential.com/wp-content/uploads/apartment-images/134143/Veris_H25_Floorplan_A5.png",
      "floorplan_note": "Floorplan: A5",
      "prices": [
        {
          "price": 5070,
          "price_range": "",
          "date_fetched": "2025-07-23 04:34:10"
        }
      ]
    },
    {
      "unit": "H25-2512",
      "building": "Haus25",
      "size": 744,
      "available_date": "2025-09-27",
      "floorplan_type": "1 bed, 1 bath",
      "floorplan_link": "https://verisresidential.com/wp-content/uploads/apartment-images/134143/Veris_H25_Floorplan_A5.png",
      "floorplan_note": "Floorplan: A5",
      "prices": [
        {
          "price": 5140,
          "price_range": "",
          "date_fetched": "2025-07-23 04:34:10"
        }
      ]
    },
    {
      "unit": "H25-1012",
      "building": "Haus25",
      "size": 744,
      "available_date": "2025-09-19",
      "floorplan_type": "1 bed, 1 bath",
      "floorplan_link": "https://verisresidential.com/wp-content/uploads/apartment-images/134143/Veris_H25_Floorplan_A5.png",
      "floorplan_note": "Floorplan: A5",
      "prices": [
        {
          "price": 5520,
          "price_range": "",
          "date_fetched": "2025-07-23 04:34:10"
        }
      ]
    },
    {
      "unit": "H25-4702",
      "building": "Haus25",
      "size": 785,
      "available_date": "2025-07-23",
      "floorplan_type": "1 bed, 1 bath",
      "floorplan_link": "https://verisresidential.com/wp-content/uploads/apartment-images/134143/Veris_H25_Floorplan_A8B.png",
      "floorplan_note": "Floorplan: A8B",
      "prices": [
        {
          "price": 5305,
          "price_range": "",
          "date_fetched": "2025-07-23 04:34:12"
        }
      ]
    },
    {
      "unit": "H25-4802",
      "building": "Haus25",
      "size": 785,
      "available_date": "2025-07-28",
      "floorplan_type": "1 bed, 1 bath",
      "floorplan_link": "https://verisresidential.com/wp-content/uploads/apartment-images/134143/Veris_H25_Floorplan_A8B.png",
      "floorplan_note": "Floorplan: A8B",
      "prices": [
        {
          "price": 5320,
          "price_range": "",
          "date_fetched": "2025-07-23 04:34:12"
        }
      ]
    },
    {
      "unit": "H25-3712",
      "building": "Haus25",
      "size": 665,
      "available_date": "2025-04-22",
      "floorplan_type": "1 bed, 1 bath",
      "floorplan_link": "https://verisresidential.com/wp-content/uploads/apartment-images/134143/Veris_H25_Floorplan_A1-1.png",
      "floorplan_note": "Floorplan: A1",
      "prices": [
        {
          "price": 5310,
          "price_range": "",
          "date_fetched": "2025-07-23 04:34:13"
        }
      ]
    },
    {
      "unit": "H25-4312",
      "building": "Haus25",
      "size": 665,
      "available_date": "2025-06-12",
      "floorplan_type": "1 bed, 1 bath",
      "floorplan_link": "https://verisresidential.com/wp-content/uploads/apartment-images/134143/Veris_H25_Floorplan_A1-1.png",
      "floorplan_note": "Floorplan: A1",
      "prices": [
        {
          "price": 5400,
          "price_range": "",
          "date_fetched": "2025-07-23 04:34:13"
        }
      ]
    },
    {
      "unit": "H25-5203",
      "building": "Haus25",
      "size": 847,
      "available_date": "2025-08-20",
      "floorplan_type": "1 bed, 1 bath",
      "floorplan_link": "https://verisresidential.com/wp-content/uploads/apartment-images/134143/Veris_H25_Floorplan_A10.png",
      "floorplan_note": "Floorplan: A10",
      "prices": [
        {
          "price": 5655,
          "price_range": "",
          "date_fetched": "2025-07-23 04:34:15"
        }
      ]
    },
    {
      "unit": "H25-3011",
      "building": "Haus25",
      "size": 865,
      "available_date": "2025-09-21",
      "floorplan_type": "1 bed, 1 bath",
      "floorplan_link": "https://verisresidential.com/wp-content/uploads/apartment-images/134143/Veris_H25_Floorplan_A15.png",
      "floorplan_note": "Floorplan: A15",
      "prices": [
        {
          "price": 6040,
          "price_range": "",
          "date_fetched": "2025-07-23 04:34:16"
        }
      ]
    },
    {
      "unit": "H25-1518",
      "building": "Haus25",
      "size": 1003,
      "available_date": "2025-09-21",
      "floorplan_type": "2 bed, 1 bath",
      "floorplan_link": "https://verisresidential.com/wp-content/uploads/apartment-images/134143/Veris_H25_Floorplan_B2.png",
      "floorplan_note": "Floorplan: B2",
      "prices": [
        {
          "price": 5820,
          "price_range": "",
          "date_fetched": "2025-07-23 04:34:18"
        }
      ]
    },
    {
      "unit": "H25-3406",
      "building": "Haus25",
      "size": 1113,
      "available_date": "2025-09-19",
      "floorplan_type": "2 bed, 2 bath",
      "floorplan_link": "https://verisresidential.com/wp-content/uploads/apartment-images/134143/Veris_H25_Floorplan_B5.png",
      "floorplan_note": "Floorplan: B5",
      "prices": [
        {
          "price": 6900,
          "price_range": "",
          "date_fetched": "2025-07-23 04:34:22"
        }
      ]
    },
    {
      "unit": "H25-4006",
      "building": "Haus25",
      "size": 1113,
      "available_date": "2025-08-25",
      "floorplan_type": "2 bed, 2 bath",
      "floorplan_link": "https://verisresidential.com/wp-content/uploads/apartment-images/134143/Veris_H25_Floorplan_B5.png",
      "floorplan_note": "Floorplan: B5",
      "prices": [
        {
          "price": 6990,
          "price_range": "",
          "date_fetched": "2025-07-23 04:34:22"
        }
      ]
    },
    {
      "unit": "H25-3106",
      "building": "Haus25",
      "size": 1113,
      "available_date": "2025-08-20",
      "floorplan_type": "2 bed, 2 bath",
      "floorplan_link": "https://verisresidential.com/wp-content/uploads/apartment-images/134143/Veris_H25_Floorplan_B5.png",
      "floorplan_note": "Floorplan: B5",
      "prices": [
        {
          "price": 9370,
          "price_range": "",
          "date_fetched": "2025-07-23 04:34:22"
        }
      ]
    },
    {
      "unit": "H25-3409",
      "building": "Haus25",
      "size": 1200,
      "available_date": "2025-09-17",
      "floorplan_type": "2 bed, 2 bath",
      "floorplan_link": "https://verisresidential.com/wp-content/uploads/apartment-images/134143/Veris_H25_Floorplan_B11.png",
      "floorplan_note": "Floorplan: B11",
      "prices": [
        {
          "price": 8155,
          "price_range": "",
          "date_fetched": "2025-07-23 04:34:26"
        }
      ]
    },
    {
      "unit": "H25-5109",
      "building": "Haus25",
      "size": 1200,
      "available_date": "2025-07-18",
      "floorplan_type": "2 bed, 2 bath",
      "floorplan_link": "https://verisresidential.com/wp-content/uploads/apartment-images/134143/Veris_H25_Floorplan_B11.png",
      "floorplan_note": "Floorplan: B11",
      "prices": [
        {
          "price": 8410,
          "price_range": "",
          "date_fetched": "2025-07-23 04:34:26"
        }
      ]
    },
    {
      "unit": "H25-5303",
      "building": "Haus25",
      "size": 1245,
      "available_date": "2025-07-22",
      "floorplan_type": "2 bed, 2 bath",
      "floorplan_link": "https://verisresidential.com/wp-content/uploads/apartment-images/134143/Veris_H25_Floorplan_B12.png",
      "floorplan_note": "Floorplan: B12",
      "prices": [
        {
          "price": 11685,
          "price_range": "",
          "date_fetched": "2025-07-23 04:34:28"
        }
      ]
    },
    {
      "unit": "H25-5501",
      "building": "Haus25",
      "size": 1349,
      "available_date": "2025-09-11",
      "floorplan_type": "2 bed, 2.5 bath",
      "floorplan_link": "https://verisresidential.com/wp-content/uploads/apartment-images/134143/Veris_H25_Floorplan_B13.png",
      "floorplan_note": "Floorplan: B13",
      "prices": [
        {
          "price": 8710,
          "price_range": "",
          "date_fetched": "2025-07-23 04:34:30"
        }
      ]
    },
    {
      "unit": "H25-5311",
      "building": "Haus25",
      "size": 1304,
      "available_date": "2025-01-27",
      "floorplan_type": "2 bed, 2.5 bath",
      "floorplan_link": "https://verisresidential.com/wp-content/uploads/apartment-images/134143/Veris_H25_Floorplan_B15.png",
      "floorplan_note": "Floorplan: B15",
      "prices": [
        {
          "price": 12600,
          "price_range": "",
          "date_fetched": "2025-07-23 04:34:32"
        }
      ]
    }
  ],
  "1grove": [],
  "warrenatyork": [
    {
      "unit": "1011",
      "building": "Warren at York",
      "size": 0,
      "available_date": "1900-01-01",
      "floorplan_type": "a4",
      "floorplan_link": "",
      "floorplan_note": "",
      "prices": [
        {
          "price": 3850.0,
          "price_range": "",
          "date_fetched": "2025-07-23 04:34:48"
        }
      ]
    },
    {
      "unit": "0311",
      "building": "Warren at York",
      "size": 0,
      "available_date": "1900-01-01",
      "floorplan_type": "a5",
      "floorplan_link": "",
      "floorplan_note": "",
      "prices": [
        {
          "price": 3900.0,
          "price_range": "",
          "date_fetched": "2025-07-23 04:34:48"
        }
      ]
    },
    {
      "unit": "0407",
      "building": "Warren at York",
      "size": 0,
      "available_date": "1900-01-01",
      "floorplan_type": "b10",
      "floorplan_link": "",
      "floorplan_note": "",
      "prices": [
        {
          "price": 5125.0,
          "price_range": "",
          "date_fetched": "2025-07-23 04:34:48"
        }
      ]
    },
    {
      "unit": "0707",
      "building": "Warren at York",
      "size": 0,
      "available_date": "1900-01-01",
      "floorplan_type": "b10",
      "floorplan_link": "",
      "floorplan_note": "",
      "prices": [
        {
          "price": 5360.0,
          "price_range": "",
          "date_fetched": "2025-07-23 04:34:48"
        }
      ]
    },
    {
      "unit": "0516",
      "building": "Warren at York",
      "size": 0,
      "available_date": "1900-01-01",
      "floorplan_type": "b3",
      "floorplan_link": "",
      "floorplan_note": "",
      "prices": [
        {
          "price": 4850.0,
          "price_range": "",
          "date_fetched": "2025-07-23 04:34:48"
        }
      ]
    },
    {
      "unit": "1013",
      "building": "Warren at York",
      "size": 0,
      "available_date": "1900-01-01",
      "floorplan_type": "bd3",
      "floorplan_link": "",
      "floorplan_note": "",
      "prices": [
        {
          "price": 6125.0,
          "price_range": "",
          "date_fetched": "2025-07-23 04:34:48"
        }
      ]
    }
  ],
  "18park": [
    {
      "unit": "0612",
      "building": "235Grand",
      "size": 0,
      "available_date": "1970-01-01",
      "floorplan_type": "",
      "floorplan_link": "",
      "floorplan_note": "",
      "prices": [
        {
          "price": "3155",
          "price_range": "3155 - - 3439",
          "date_fetched": "2025-07-23 04:34:52"
        }
      ]
    },
    {
      "unit": "0638",
      "building": "235Grand",
      "size": 0,
      "available_date": "1970-01-01",
      "floorplan_type": "",
      "floorplan_link": "",
      "floorplan_note": "",
      "prices": [
        {
          "price": "3125",
          "price_range": "3125 - - 3407",
          "date_fetched": "2025-07-23 04:34:52"
        }
      ]
    },
    {
      "unit": "PH02",
      "building": "235Grand",
      "size": 0,
      "available_date": "2025-08-13",
      "floorplan_type": "",
      "floorplan_link": "",
      "floorplan_note": "",
      "prices": [
        {
          "price": "3150",
          "price_range": "3150 - - 3455",
          "date_fetched": "2025-07-23 04:34:52"
        }
      ]
    },
    {
      "unit": "0312",
      "building": "235Grand",
      "size": 0,
      "available_date": "2025-08-15",
      "floorplan_type": "",
      "floorplan_link": "",
      "floorplan_note": "",
      "prices": [
        {
          "price": "3055",
          "price_range": "3055 - - 3344",
          "date_fetched": "2025-07-23 04:34:53"
        }
      ]
    },
    {
      "unit": "PH25",
      "building": "235Grand",
      "size": 0,
      "available_date": "1970-01-01",
      "floorplan_type": "",
      "floorplan_link": "",
      "floorplan_note": "",
      "prices": [
        {
          "price": "3691",
          "price_range": "3691 - - 4030",
          "date_fetched": "2025-07-23 04:34:56"
        }
      ]
    },
    {
      "unit": "0506",
      "building": "235Grand",
      "size": 0,
      "available_date": "2025-08-07",
      "floorplan_type": "",
      "floorplan_link": "",
      "floorplan_note": "",
      "prices": [
        {
          "price": "3824",
          "price_range": "3824 - - 4195",
          "date_fetched": "2025-07-23 04:34:56"
        }
      ]
    },
    {
      "unit": "0931",
      "building": "235Grand",
      "size": 0,
      "available_date": "2025-08-07",
      "floorplan_type": "",
      "floorplan_link": "",
      "floorplan_note": "",
      "prices": [
        {
          "price": "3791",
          "price_range": "3791 - - 4159",
          "date_fetched": "2025-07-23 04:34:56"
        }
      ]
    },
    {
      "unit": "0513",
      "building": "235Grand",
      "size": 0,
      "available_date": "2025-09-07",
      "floorplan_type": "",
      "floorplan_link": "",
      "floorplan_note": "",
      "prices": [
        {
          "price": "3571",
          "price_range": "3571 - - 3927",
          "date_fetched": "2025-07-23 04:34:56"
        }
      ]
    },
    {
      "unit": "0832",
      "building": "235Grand",
      "size": 0,
      "available_date": "2025-09-07",
      "floorplan_type": "",
      "floorplan_link": "",
      "floorplan_note": "",
      "prices": [
        {
          "price": "3859",
          "price_range": "3859 - - 4236",
          "date_fetched": "2025-07-23 04:34:56"
        }
      ]
    },
    {
      "unit": "PH32",
      "building": "235Grand",
      "size": 0,
      "available_date": "2025-09-07",
      "floorplan_type": "",
      "floorplan_link": "",
      "floorplan_note": "",
      "prices": [
        {
          "price": "3809",
          "price_range": "3809 - - 4182",
          "date_fetched": "2025-07-23 04:34:56"
        }
      ]
    },
    {
      "unit": "PH35",
      "building": "235Grand",
      "size": 0,
      "available_date": "2025-09-07",
      "floorplan_type": "",
      "floorplan_link": "",
      "floorplan_note": "",
      "prices": [
        {
          "price": "3741",
          "price_range": "3741 - - 4109",
          "date_fetched": "2025-07-23 04:34:56"
        }
      ]
    },
    {
      "unit": "0730",
      "building": "235Grand",
      "size": 0,
      "available_date": "2025-10-01",
      "floorplan_type": "",
      "floorplan_link": "",
      "floorplan_note": "",
      "prices": [
        {
          "price": "3834",
          "price_range": "3834 - - 4216",
          "date_fetched": "2025-07-23 04:34:56"
        }
      ]
    },
    {
      "unit": "0840",
      "building": "235Grand",
      "size": 0,
      "available_date": "2025-10-16",
      "floorplan_type": "",
      "floorplan_link": "",
      "floorplan_note": "",
      "prices": [
        {
          "price": "3943",
          "price_range": "3943 - - 4323",
          "date_fetched": "2025-07-23 04:34:56"
        }
      ]
    },
    {
      "unit": "0401",
      "building": "235Grand",
      "size": 0,
      "available_date": "2025-09-07",
      "floorplan_type": "",
      "floorplan_link": "",
      "floorplan_note": "",
      "prices": [
        {
          "price": "5058",
          "price_range": "5058 - - 5562",
          "date_fetched": "2025-07-23 04:35:00"
        }
      ]
    },
    {
      "unit": "0739",
      "building": "235Grand",
      "size": 0,
      "available_date": "2025-09-07",
      "floorplan_type": "",
      "floorplan_link": "",
      "floorplan_note": "",
      "prices": [
        {
          "price": "5433",
          "price_range": "5433 - - 5965",
          "date_fetched": "2025-07-23 04:35:00"
        }
      ]
    },
    {
      "unit": "0719",
      "building": "235Grand",
      "size": 0,
      "available_date": "2025-09-16",
      "floorplan_type": "",
      "floorplan_link": "",
      "floorplan_note": "",
      "prices": [
        {
          "price": "5458",
          "price_range": "5458 - - 6141",
          "date_fetched": "2025-07-23 04:35:00"
        }
      ]
    },
    {
      "unit": "0409",
      "building": "235Grand",
      "size": 0,
      "available_date": "2025-10-07",
      "floorplan_type": "",
      "floorplan_link": "",
      "floorplan_note": "",
      "prices": [
        {
          "price": "5412",
          "price_range": "5412 - - 5934",
          "date_fetched": "2025-07-23 04:35:00"
        }
      ]
    }
  ],
  "235grand": [
    {
      "unit": "4410",
      "building": "235Grand",
      "size": 0,
      "available_date": "1970-01-01",
      "floorplan_type": "",
      "floorplan_link": "",
      "floorplan_note": "",
      "prices": [
        {
          "price": "3244",
          "price_range": "3244 - - 4035",
          "date_fetched": "2025-07-23 04:35:04"
        }
      ]
    },
    {
      "unit": "3613",
      "building": "235Grand",
      "size": 0,
      "available_date": "1970-01-01",
      "floorplan_type": "",
      "floorplan_link": "",
      "floorplan_note": "",
      "prices": [
        {
          "price": "3664",
          "price_range": "3664 - - 4499",
          "date_fetched": "2025-07-23 04:35:04"
        }
      ]
    },
    {
      "unit": "3813",
      "building": "235Grand",
      "size": 0,
      "available_date": "1970-01-01",
      "floorplan_type": "",
      "floorplan_link": "",
      "floorplan_note": "",
      "prices": [
        {
          "price": "3714",
          "price_range": "3714 - - 4556",
          "date_fetched": "2025-07-23 04:35:04"
        }
      ]
    },
    {
      "unit": "0413",
      "building": "235Grand",
      "size": 0,
      "available_date": "2025-07-29",
      "floorplan_type": "",
      "floorplan_link": "",
      "floorplan_note": "",
      "prices": [
        {
          "price": "3289",
          "price_range": "3289 - - 4113",
          "date_fetched": "2025-07-23 04:35:04"
        }
      ]
    },
    {
      "unit": "3911",
      "building": "235Grand",
      "size": 0,
      "available_date": "2025-08-26",
      "floorplan_type": "",
      "floorplan_link": "",
      "floorplan_note": "",
      "prices": [
        {
          "price": "3364",
          "price_range": "3364 - - 4177",
          "date_fetched": "2025-07-23 04:35:04"
        }
      ]
    },
    {
      "unit": "3010",
      "building": "235Grand",
      "size": 0,
      "available_date": "2025-09-07",
      "floorplan_type": "",
      "floorplan_link": "",
      "floorplan_note": "",
      "prices": [
        {
          "price": "3219",
          "price_range": "3219 - - 4030",
          "date_fetched": "2025-07-23 04:35:04"
        }
      ]
    },
    {
      "unit": "3407",
      "building": "235Grand",
      "size": 0,
      "available_date": "2025-09-07",
      "floorplan_type": "",
      "floorplan_link": "",
      "floorplan_note": "",
      "prices": [
        {
          "price": "3469",
          "price_range": "3469 - - 4317",
          "date_fetched": "2025-07-23 04:35:04"
        }
      ]
    },
    {
      "unit": "3510",
      "building": "235Grand",
      "size": 0,
      "available_date": "2025-09-07",
      "floorplan_type": "",
      "floorplan_link": "",
      "floorplan_note": "",
      "prices": [
        {
          "price": "3269",
          "price_range": "3269 - - 4087",
          "date_fetched": "2025-07-23 04:35:04"
        }
      ]
    },
    {
      "unit": "2811",
      "building": "235Grand",
      "size": 0,
      "available_date": "2025-09-23",
      "floorplan_type": "",
      "floorplan_link": "",
      "floorplan_note": "",
      "prices": [
        {
          "price": "3224",
          "price_range": "3224 - - 4044",
          "date_fetched": "2025-07-23 04:35:04"
        }
      ]
    },
    {
      "unit": "1707",
      "building": "235Grand",
      "size": 0,
      "available_date": "2025-10-07",
      "floorplan_type": "",
      "floorplan_link": "",
      "floorplan_note": "",
      "prices": [
        {
          "price": "3309",
          "price_range": "3309 - - 4142",
          "date_fetched": "2025-07-23 04:35:04"
        }
      ]
    },
    {
      "unit": "1607",
      "building": "235Grand",
      "size": 0,
      "available_date": "2025-10-24",
      "floorplan_type": "",
      "floorplan_link": "",
      "floorplan_note": "",
      "prices": [
        {
          "price": "3299",
          "price_range": "3299 - - 4121",
          "date_fetched": "2025-07-23 04:35:04"
        }
      ]
    },
    {
      "unit": "4411",
      "building": "235Grand",
      "size": 0,
      "available_date": "2025-11-02",
      "floorplan_type": "",
      "floorplan_link": "",
      "floorplan_note": "",
      "prices": [
        {
          "price": "3399",
          "price_range": "3399 - - 4217",
          "date_fetched": "2025-07-23 04:35:04"
        }
      ]
    },
    {
      "unit": "1109",
      "building": "235Grand",
      "size": 0,
      "available_date": "2025-08-07",
      "floorplan_type": "",
      "floorplan_link": "",
      "floorplan_note": "",
      "prices": [
        {
          "price": "4041",
          "price_range": "4041 - - 5051",
          "date_fetched": "2025-07-23 04:35:08"
        }
      ]
    },
    {
      "unit": "2504",
      "building": "235Grand",
      "size": 0,
      "available_date": "2025-08-07",
      "floorplan_type": "",
      "floorplan_link": "",
      "floorplan_note": "",
      "prices": [
        {
          "price": "3741",
          "price_range": "3741 - - 4706",
          "date_fetched": "2025-07-23 04:35:08"
        }
      ]
    },
    {
      "unit": "2602",
      "building": "235Grand",
      "size": 0,
      "available_date": "2025-08-07",
      "floorplan_type": "",
      "floorplan_link": "",
      "floorplan_note": "",
      "prices": [
        {
          "price": "3851",
          "price_range": "3851 - - 4832",
          "date_fetched": "2025-07-23 04:35:08"
        }
      ]
    },
    {
      "unit": "3512",
      "building": "235Grand",
      "size": 0,
      "available_date": "2025-08-07",
      "floorplan_type": "",
      "floorplan_link": "",
      "floorplan_note": "",
      "prices": [
        {
          "price": "3891",
          "price_range": "3891 - - 4878",
          "date_fetched": "2025-07-23 04:35:08"
        }
      ]
    },
    {
      "unit": "3809",
      "building": "235Grand",
      "size": 0,
      "available_date": "2025-08-07",
      "floorplan_type": "",
      "floorplan_link": "",
      "floorplan_note": "",
      "prices": [
        {
          "price": "4201",
          "price_range": "4201 - - 5235",
          "date_fetched": "2025-07-23 04:35:08"
        }
      ]
    },
    {
      "unit": "4108",
      "building": "235Grand",
      "size": 0,
      "available_date": "2025-08-07",
      "floorplan_type": "",
      "floorplan_link": "",
      "floorplan_note": "",
      "prices": [
        {
          "price": "3936",
          "price_range": "3936 - - 4930",
          "date_fetched": "2025-07-23 04:35:09"
        }
      ]
    },
    {
      "unit": "3612",
      "building": "235Grand",
      "size": 0,
      "available_date": "2025-08-13",
      "floorplan_type": "",
      "floorplan_link": "",
      "floorplan_note": "",
      "prices": [
        {
          "price": "3891",
          "price_range": "3891 - - 4889",
          "date_fetched": "2025-07-23 04:35:09"
        }
      ]
    },
    {
      "unit": "4208",
      "building": "235Grand",
      "size": 0,
      "available_date": "2025-08-15",
      "floorplan_type": "",
      "floorplan_link": "",
      "floorplan_note": "",
      "prices": [
        {
          "price": "3951",
          "price_range": "3951 - - 4936",
          "date_fetched": "2025-07-23 04:35:09"
        }
      ]
    },
    {
      "unit": "4502",
      "building": "235Grand",
      "size": 0,
      "available_date": "2025-08-22",
      "floorplan_type": "",
      "floorplan_link": "",
      "floorplan_note": "",
      "prices": [
        {
          "price": "3941",
          "price_range": "3941 - - 4914",
          "date_fetched": "2025-07-23 04:35:09"
        }
      ]
    },
    {
      "unit": "0623",
      "building": "235Grand",
      "size": 0,
      "available_date": "2025-09-07",
      "floorplan_type": "",
      "floorplan_link": "",
      "floorplan_note": "",
      "prices": [
        {
          "price": "3916",
          "price_range": "3916 - - 4863",
          "date_fetched": "2025-07-23 04:35:09"
        }
      ]
    },
    {
      "unit": "2702",
      "building": "235Grand",
      "size": 0,
      "available_date": "2025-09-07",
      "floorplan_type": "",
      "floorplan_link": "",
      "floorplan_note": "",
      "prices": [
        {
          "price": "3851",
          "price_range": "3851 - - 4788",
          "date_fetched": "2025-07-23 04:35:09"
        }
      ]
    },
    {
      "unit": "3308",
      "building": "235Grand",
      "size": 0,
      "available_date": "2025-09-07",
      "floorplan_type": "",
      "floorplan_link": "",
      "floorplan_note": "",
      "prices": [
        {
          "price": "3896",
          "price_range": "3896 - - 4840",
          "date_fetched": "2025-07-23 04:35:09"
        }
      ]
    },
    {
      "unit": "3412",
      "building": "235Grand",
      "size": 0,
      "available_date": "2025-09-07",
      "floorplan_type": "",
      "floorplan_link": "",
      "floorplan_note": "",
      "prices": [
        {
          "price": "3891",
          "price_range": "3891 - - 4834",
          "date_fetched": "2025-07-23 04:35:09"
        }
      ]
    },
    {
      "unit": "3902",
      "building": "235Grand",
      "size": 0,
      "available_date": "2025-09-07",
      "floorplan_type": "",
      "floorplan_link": "",
      "floorplan_note": "",
      "prices": [
        {
          "price": "3911",
          "price_range": "3911 - - 4857",
          "date_fetched": "2025-07-23 04:35:09"
        }
      ]
    },
    {
      "unit": "1608",
      "building": "235Grand",
      "size": 0,
      "available_date": "2025-09-13",
      "floorplan_type": "",
      "floorplan_link": "",
      "floorplan_note": "",
      "prices": [
        {
          "price": "3786",
          "price_range": "3786 - - 4724",
          "date_fetched": "2025-07-23 04:35:09"
        }
      ]
    },
    {
      "unit": "0322",
      "building": "235Grand",
      "size": 0,
      "available_date": "2025-09-30",
      "floorplan_type": "",
      "floorplan_link": "",
      "floorplan_note": "",
      "prices": [
        {
          "price": "3841",
          "price_range": "3841 - - 4788",
          "date_fetched": "2025-07-23 04:35:09"
        }
      ]
    },
    {
      "unit": "1904",
      "building": "235Grand",
      "size": 0,
      "available_date": "2025-10-07",
      "floorplan_type": "",
      "floorplan_link": "",
      "floorplan_note": "",
      "prices": [
        {
          "price": "3686",
          "price_range": "3686 - - 4603",
          "date_fetched": "2025-07-23 04:35:09"
        }
      ]
    },
    {
      "unit": "2312",
      "building": "235Grand",
      "size": 0,
      "available_date": "2025-10-07",
      "floorplan_type": "",
      "floorplan_link": "",
      "floorplan_note": "",
      "prices": [
        {
          "price": "3696",
          "price_range": "3696 - - 4615",
          "date_fetched": "2025-07-23 04:35:09"
        }
      ]
    },
    {
      "unit": "3709",
      "building": "235Grand",
      "size": 0,
      "available_date": "2025-10-07",
      "floorplan_type": "",
      "floorplan_link": "",
      "floorplan_note": "",
      "prices": [
        {
          "price": "4206",
          "price_range": "4206 - - 5202",
          "date_fetched": "2025-07-23 04:35:09"
        }
      ]
    },
    {
      "unit": "4403",
      "building": "235Grand",
      "size": 0,
      "available_date": "2025-10-07",
      "floorplan_type": "",
      "floorplan_link": "",
      "floorplan_note": "",
      "prices": [
        {
          "price": "4076",
          "price_range": "4076 - - 5052",
          "date_fetched": "2025-07-23 04:35:09"
        }
      ]
    },
    {
      "unit": "3001",
      "building": "235Grand",
      "size": 0,
      "available_date": "2025-11-07",
      "floorplan_type": "",
      "floorplan_link": "",
      "floorplan_note": "",
      "prices": [
        {
          "price": "3979",
          "price_range": "3979 - - 4948",
          "date_fetched": "2025-07-23 04:35:09"
        }
      ]
    },
    {
      "unit": "3403",
      "building": "235Grand",
      "size": 0,
      "available_date": "2025-11-07",
      "floorplan_type": "",
      "floorplan_link": "",
      "floorplan_note": "",
      "prices": [
        {
          "price": "3999",
          "price_range": "3999 - - 4971",
          "date_fetched": "2025-07-23 04:35:09"
        }
      ]
    },
    {
      "unit": "0305",
      "building": "235Grand",
      "size": 0,
      "available_date": "2025-08-07",
      "floorplan_type": "",
      "floorplan_link": "",
      "floorplan_note": "",
      "prices": [
        {
          "price": "5539",
          "price_range": "5539 - - 6953",
          "date_fetched": "2025-07-23 04:35:13"
        }
      ]
    },
    {
      "unit": "4105",
      "building": "235Grand",
      "size": 0,
      "available_date": "2025-09-05",
      "floorplan_type": "",
      "floorplan_link": "",
      "floorplan_note": "",
      "prices": [
        {
          "price": "5789",
          "price_range": "5789 - - 7211",
          "date_fetched": "2025-07-23 04:35:13"
        }
      ]
    },
    {
      "unit": "2205",
      "building": "235Grand",
      "size": 0,
      "available_date": "2025-09-07",
      "floorplan_type": "",
      "floorplan_link": "",
      "floorplan_note": "",
      "prices": [
        {
          "price": "5639",
          "price_range": "5639 - - 7006",
          "date_fetched": "2025-07-23 04:35:13"
        }
      ]
    },
    {
      "unit": "3506",
      "building": "235Grand",
      "size": 0,
      "available_date": "2025-09-07",
      "floorplan_type": "",
      "floorplan_link": "",
      "floorplan_note": "",
      "prices": [
        {
          "price": "5439",
          "price_range": "5439 - - 6776",
          "date_fetched": "2025-07-23 04:35:13"
        }
      ]
    },
    {
      "unit": "4306",
      "building": "235Grand",
      "size": 0,
      "available_date": "2025-09-07",
      "floorplan_type": "",
      "floorplan_link": "",
      "floorplan_note": "",
      "prices": [
        {
          "price": "5514",
          "price_range": "5514 - - 6863",
          "date_fetched": "2025-07-23 04:35:13"
        }
      ]
    },
    {
      "unit": "2705",
      "building": "235Grand",
      "size": 0,
      "available_date": "2025-10-07",
      "floorplan_type": "",
      "floorplan_link": "",
      "floorplan_note": "",
      "prices": [
        {
          "price": "5697",
          "price_range": "5697 - - 7080",
          "date_fetched": "2025-07-23 04:35:13"
        }
      ]
    }
  ]
}